Functions/SIP.py
Functions/__init__.py
Functions/aritmatich.py
Functions/colors.py
Functions/filters.py
Functions/hist.py
Functions/rotate.py
sipa/__init__.py
sipa/main.py
sipa/core/__init__.py
sipa/core/arithmetic.py
sipa/core/colors.py
sipa/core/filters.py
sipa/core/histogram.py
sipa/core/rotate.py
sipa/gui/__init__.py
sipa/gui/main_window.py
sipa/gui/ui_main_window.py
sipa-0.2.0.dist-info/licenses/LICENSE
tests/__init__.py
tests/test_core.py
sipa-0.2.0.dist-info/METADATA
sipa-0.2.0.dist-info/WHEEL
sipa-0.2.0.dist-info/entry_points.txt
sipa-0.2.0.dist-info/top_level.txt
sipa-0.2.0.dist-info/RECORD
