Metadata-Version: 2.4
Name: sipa
Version: 0.2.0
Summary: Simple Image Processing Application - A GUI-based image processing tool
Home-page: https://github.com/haydarkadioglu/simple-image-processing-application
Author: Haydar Kadıoğlu
Author-email: Haydar Kadıoğlu <a.haydar.kadioglu@gmail.com>
License-Expression: MIT
Project-URL: Homepage, https://github.com/haydarkadioglu/simple-image-processing-application
Project-URL: Bug Reports, https://github.com/haydarkadioglu/simple-image-processing-application/issues
Project-URL: Source, https://github.com/haydarkadioglu/simple-image-processing-application
Keywords: image-processing,gui,pyqt5,computer-vision,image-filters
Classifier: Development Status :: 4 - Beta
Classifier: Intended Audience :: Developers
Classifier: Intended Audience :: Education
Classifier: Operating System :: OS Independent
Classifier: Programming Language :: Python :: 3
Classifier: Programming Language :: Python :: 3.7
Classifier: Programming Language :: Python :: 3.8
Classifier: Programming Language :: Python :: 3.9
Classifier: Programming Language :: Python :: 3.10
Classifier: Programming Language :: Python :: 3.11
Classifier: Topic :: Scientific/Engineering :: Image Processing
Classifier: Topic :: Software Development :: Libraries :: Python Modules
Classifier: Topic :: Multimedia :: Graphics
Requires-Python: >=3.7
License-File: LICENSE
Requires-Dist: numpy>=1.19.0
Requires-Dist: matplotlib>=3.3.0
Requires-Dist: PyQt5>=5.15.0
Requires-Dist: opencv-python>=4.5.0
Provides-Extra: dev
Requires-Dist: pytest>=6.0; extra == "dev"
Requires-Dist: black>=21.0; extra == "dev"
Requires-Dist: flake8>=3.8; extra == "dev"
Dynamic: author
Dynamic: home-page
Dynamic: license-file
Dynamic: requires-python
